MANIFEST.in
README.rst
setup.py
bade/__init__.py
bade/build.py
bade/cli.py
bade/config.py
bade/index.py
bade/utils.py
bade.egg-info/PKG-INFO
bade.egg-info/SOURCES.txt
bade.egg-info/dependency_links.txt
bade.egg-info/entry_points.txt
bade.egg-info/requires.txt
bade.egg-info/top_level.txt
bade/build/page.py
bade/build/post.py
bade/directives/dotgraph.py
bade/directives/eqtexsvg.py
bade/directives/pygments.py
templates/base.html
templates/blog.rst
templates/header.html
templates/index.html
templates/page.html
templates/post.html
templates/prev_next.html