Metadata-Version: 1.0
Name: bade
Version: 0.2.2
Summary: Micro-blogging with rST
Home-page: http://bmcorser.github.com/bade
Author: bmcorser
Author-email: bmcorser@gmail.com
License: UNKNOWN
Platform: UNKNOWN
